{
  "classname": null,
  "name": null,
  "animation": {
    "classname": null,
    "name": "AnimationManager",
    "actionlist": []
  },
  "dataScale": 1,
  "designHeight": 800,
  "designWidth": 480,
  "textures": [],
  "texturesPng": [
    "9for_bg.png",
    "sound_off.png",
    "set_back.png",
    "an_tc.png",
    "an_bz.png",
    "set_about.png",
    "set_3.png",
    "sound.png",
    "an_ye.png",
    "set_hlep.png",
    "huangse.png",
    "white.png",
    "Button_Close.png",
    "jiugongge.png",
    "biaoti_shang_dalibao1.png",
    "dingtiao.png",
    "ditiao.png",
    "ganendalibao.png",
    "tishi1.png",
    "short_message_15.png",
    "jiugongge_xin.png",
    "guangsu_xin.png",
    "dalibao.png",
    "lijihuode.png",
    "zengsong_xin.png",
    "1f2.png",
    "wenzimiaoshu.png",
    "x10.png",
    "lanbaoshi.png",
    "10y.png",
    "x150.png",
    "1j.png",
    "15y.png",
    "x250.png",
    "29y.png",
    "x500.png",
    "xdlbao.png",
    "zengbig_unicom.png",
    "x300.png",
    "x200.png",
    "18y.png",
    "x360.png",
    "1y.png",
    "x20.png",
    "2y.png",
    "x40.png",
    "5y.png",
    "x65.png",
    "zhong4.png",
    "shang4.png",
    "zif.png",
    "x230.png",
    "2j.png",
    "14y.png",
    "rankitem_common_2.png",
    "paihangbang_jiangbei.png",
    "onsale_btn_1.png",
    "rankitem_common_1.png",
    "check.png",
    "9for_bg.png",
    "shop_item_bg.png",
    "onsale_btn.png",
    "qbjs.png",
    "gb.png",
    "yjx_log.png",
    "9for_bg.png",
    "onsale_btn.png",
    "BtnSureYellow.png",
    "rankitem_owner_1.png",
    "paihangbang_jiangbei.png",
    "rankitem_owner_2.png",
    "9for_bg.png",
    "gb.png",
    "infos_title.png",
    "white.png",
    "onsale_btn.png",
    "sk_gift_tgjl.png",
    "x5.png",
    "tgjllb.png",
    "Bg_Stage.jpg",
    "popstar_start.png",
    "popstar_continue.png",
    "file_symbol.png",
    "Button_Shop.png",
    "menu_btn.png",
    "CDKEY_btn.png",
    "gift_btn.png",
    "coin_bar.png",
    "logo_xin_1.png",
    "paihangbang.png",
    "1fqlb.png",
    "btn_email.png",
    "youjian_1.png",
    "onsale_1_btn.png",
    "j3.png",
    "qipao.png",
    "ImageContinue.png",
    "ImageFree.png",
    "jinbi_tiao.png",
    "btn_11.png",
    "btn_6.png",
    "blue.png",
    "huodong.png",
    "moregame_btn.png",
    "zzcj01.png",
    "hotsale_bg.png",
    "Sign_Money_50x49.png",
    "zengbig.png",
    "onsale_btn.png",
    "white.png",
    "gb.png",
    "tishi1.png",
    "onsaleTitle_xsyh.png",
    "onsale_mm.png",
    "onsale_btn.png",
    "white.png",
    "Button_Close.png",
    "tishi1.png",
    "salegift.png",
    "x150.png",
    "hotsale_bg.png",
    "Sign_Money_50x49.png",
    "zengsong.png",
    "onsale_btn.png",
    "white.png",
    "gb.png",
    "tishi1.png",
    "onsaleTitle_xsyh.png",
    "text_yhlb.png",
    "huodong_diban_2.png",
    "Button_Close.png",
    "huodongzhongxin.png",
    "btn_activity_task.png",
    "btn_activity_task_ban.png",
    "title_silk_zise.png",
    "faild_Get_Net.png",
    "no_activity.png",
    "huodong_diban_2.png",
    "huodong_diban.png",
    "title_silk_zise.png",
    "huodongxiaotieshi.png",
    "Button_Close.png",
    "rankitem_owner_xin.png",
    "Bg_Stage.jpg",
    "gguangshu.png",
    "coin_bar.png",
    "jinbi_tiao.png",
    "dangqianfenshu.png",
    "jiesuo_tiao.png",
    "j3.png",
    "huodejinbi.png",
    "onsale_2_btn.png",
    "nqzr.png",
    "tongguananniu_btn.png",
    "zaiyici.png",
    "ImageFree.png",
    "onsale_btn.png",
    "qipao.png",
    "rankitem_common_1.png",
    "gold.png",
    "Bg_Stage.jpg",
    "Bg_Matrix_4.png",
    "Bg_Matrix_4_Line0.png",
    "white.png",
    "Image_ProgressBar.png",
    "dituyinying.png",
    "Text_Stage.png",
    "Button_Pause.png",
    "TextScoreTop.png",
    "coin_bar.png",
    "jiahao.png",
    "jinbi_tiao.png",
    "Button_Line_1.png",
    "Button_Line_2.png",
    "zuanshidiban_1111.png",
    "Sign_Money_50x49.png",
    "Button_Same_1.png",
    "Button_Same_2.png",
    "j3.png",
    "Button_huojian_1.png",
    "Button_huojian_0.png",
    "Button_huojian_2.png",
    "Button_Stop_1.png",
    "Button_Stop_2.png",
    "Text_StageEnd.png",
    "Bg_PanelPause.png",
    "Button_Close.png",
    "white.png",
    "Sign_Page_0.png",
    "white.png",
    "Button_Continue_0.png",
    "Button_Continue_1.png",
    "Button_SoundOff_0.png",
    "Button_SoundOn_0.png",
    "Button_Home_0.png",
    "Button_Home_1.png",
    "Button_Help_0.png",
    "Button_Help_1.png",
    "white.png",
    "jixutongguan.png",
    "lvse.png",
    "tongguananniu_wenzi.png",
    "Button_Close.png",
    "jixutongguan_juese.png",
    "coin_bar.png",
    "white.png",
    "zuanshidiban.png",
    "xiaozuanshi.png",
    "game_prp_numbg.png",
    "Props_Bomb.png",
    "Props_Rainbow.png",
    "Props_Paint.png",
    "pause.png",
    "jiahao.png",
    "btn_6.png",
    "blue.png",
    "menu_bg.png",
    "arrow.png",
    "purple.png",
    "green.png",
    "blue.png",
    "yellow.png",
    "red.png",
    "back.png",
    "connected_not.png",
    "connected.png",
    "Props_Bomb.png",
    "Props_Paint.png",
    "Props_Rainbow.png",
    "continue.png",
    "exit.png",
    "star_sound.png",
    "logo_pic.png",
    "bg_sunburst1.png",
    "Sign_Money_50x49.png",
    "exit.png",
    "result_bg1.png",
    "retry.png",
    "jixutongguan.png",
    "lvse.png",
    "tongguananniu_wenzi.png",
    "Button_Close.png",
    "jixutongguan_juese.png",
    "huodong_diban_2.png",
    "Button_Close.png",
    "Button_Close1.png",
    "onsale_2_btn.png",
    "white.png",
    "Bg_Stage.jpg",
    "ButtonYellowBig.png",
    "ButtonGreenSmall.png",
    "logo_xin_1.png",
    "lvse.png",
    "white.png",
    "Button_Close.png",
    "hotsale_bg_2.png",
    "jinbilibao.png",
    "title_silk_22.png",
    "goumaijinbi.jpg",
    "x1888.png",
    "jikehuode.png",
    "jikegoumai.png",
    "tishi1.png",
    "short_message_9.png",
    "Sign_Money_50x49.png",
    "huodong_diban_2.png",
    "Button_Close.png",
    "shop_item_bg-2.png",
    "shangdian_biaotoutu.png",
    "shangdian_wenzi.png",
    "white.png",
    "shop_item_bg-1.png",
    "zengss.png",
    "btn_2_1.png",
    "duanxinzhifu-1.png",
    "duanxinzhifu-2.png",
    "360zhifu-1.png",
    "360zhifu-2.png",
    "shangdian_zengong.png",
    "jinbijiekou.png",
    "Button_Close.png",
    "white.png",
    "zhongjian.png",
    "tongguananniu.png",
    "lingqu.png",
    "Button_Close.png",
    "ditiao.png",
    "dingtiao.png",
    "biaotou1.png",
    "zhong2.png",
    "huangse.png",
    "lingquhuang.png",
    "biaotou2.png",
    "zhong4.png",
    "shang4.png",
    "zif.png",
    "zhong5.png",
    "queding5.png",
    "biaotou5.png",
    "zhong3.png",
    "huangse.png",
    "lkijishiyong.png",
    "Button_Close.png",
    "biaotou3.png",
    "zif.png",
    "ditiao.png",
    "dingtiao.png",
    "bgt001.jpg",
    "wzbt.png",
    "mddb.png",
    "white.png",
    "mejpdb.png",
    "menu_help.png",
    "Button_Close.png",
    "ljcz01.png",
    "ljcz03.png",
    "ljcz02.png",
    "an_cj.png",
    "cjdb01.png",
    "jpdb.png",
    "jpdb01.png",
    "jiugongge.png",
    "dingtiao.png",
    "choujiangjieguo02.png",
    "title_silk.png",
    "choujiangjieguo01.png",
    "ka001.png",
    "ka004.png",
    "choujiangjieguo04.png",
    "choujiangjieguo03.png",
    "ditiao.png",
    "jiugongge.png",
    "shouji01.png",
    "yaoqinghaoyoushu.png",
    "shouji02.png",
    "ditiao.png",
    "dingtiao.png",
    "Button_Close.png",
    "xlb01.png",
    "xlb.png",
    "white.png",
    "Button_Close.png",
    "smdb.png"
  ],
  "version": "1.6.0.0",
  "widgetTree": {
    "classname": "Panel",
    "name": null,
    "children": [
      {
        "classname": "ImageView",
        "name": null,
        "children": [
          {
            "classname": "Label",
            "name": null,
            "children": [],
            "options": {
              "__type": "LabelSurrogate:#EditorCommon.JsonModel.Component.GUI",
              "classname": "Label",
              "name": "TextTitle",
              "ZOrder": 2,
              "actiontag": 783878,
              "anchorPointX": 0.5,
              "anchorPointY": 0.5,
              "classType": "CocoStudio.EngineAdapterWrap.CSLabel",
              "colorB": 255,
              "colorG": 255,
              "colorR": 255,
              "customProperty": "",
              "flipX": false,
              "flipY": false,
              "height": 31,
              "ignoreSize": true,
              "layoutParameter": null,
              "opacity": 255,
              "positionPercentX": 0,
              "positionPercentY": 0.6242038,
              "positionType": 0,
              "rotation": 0,
              "scaleX": 1,
              "scaleY": 1,
              "sizePercentX": 0.210989013,
              "sizePercentY": 0.0987261161,
              "sizeType": 0,
              "tag": 73397,
              "touchAble": false,
              "useMergedTexture": false,
              "visible": true,
              "width": 96,
              "x": 0,
              "y": 196,
              "areaHeight": 0,
              "areaWidth": 0,
              "fontFile": null,
              "fontName": "微软雅黑",
              "fontSize": 24,
              "hAlignment": 0,
              "text": "活动规则",
              "touchScaleEnable": false,
              "vAlignment": 0
            }
          },
          {
            "classname": "Button",
            "name": null,
            "children": [],
            "options": {
              "__type": "ButtonSurrogate:#EditorCommon.JsonModel.Component.GUI",
              "classname": "Button",
              "name": "ButtonClose",
              "ZOrder": 11,
              "actiontag": 36824405,
              "anchorPointX": 0.5,
              "anchorPointY": 0.5,
              "classType": "CocoStudio.EngineAdapterWrap.CSButton",
              "colorB": 255,
              "colorG": 255,
              "colorR": 255,
              "customProperty": "",
              "flipX": false,
              "flipY": false,
              "height": 60,
              "ignoreSize": true,
              "layoutParameter": null,
              "opacity": 255,
              "positionPercentX": 0.437362641,
              "positionPercentY": 0.614649653,
              "positionType": 0,
              "rotation": 0,
              "scaleX": 0.9,
              "scaleY": 0.9,
              "sizePercentX": 0.127472535,
              "sizePercentY": 0.1910828,
              "sizeType": 0,
              "tag": 73396,
              "touchAble": true,
              "useMergedTexture": false,
              "visible": true,
              "width": 58,
              "x": 199,
              "y": 193,
              "capInsetsHeight": 0,
              "capInsetsWidth": 0,
              "capInsetsX": 0,
              "capInsetsY": 0,
              "disabled": null,
              "disabledData": {
                "path": null,
                "plistFile": null,
                "resourceType": 0
              },
              "fontName": "微软雅黑",
              "fontSize": 14,
              "fontType": 0,
              "normal": null,
              "normalData": {
                "path": "Button_Close.png",
                "plistFile": "",
                "resourceType": 0
              },
              "pressed": null,
              "pressedData": {
                "path": null,
                "plistFile": null,
                "resourceType": 0
              },
              "scale9Enable": false,
              "scale9Height": 60,
              "scale9Width": 58,
              "text": "",
              "textColorB": 255,
              "textColorG": 255,
              "textColorR": 255
            }
          },
          {
            "classname": "Label",
            "name": null,
            "children": [],
            "options": {
              "__type": "LabelSurrogate:#EditorCommon.JsonModel.Component.GUI",
              "classname": "Label",
              "name": "Label_5",
              "ZOrder": 4,
              "actiontag": 57408296,
              "anchorPointX": 0.5,
              "anchorPointY": 0.5,
              "classType": "CocoStudio.EngineAdapterWrap.CSLabel",
              "colorB": 255,
              "colorG": 255,
              "colorR": 255,
              "customProperty": "",
              "flipX": false,
              "flipY": false,
              "height": 24,
              "ignoreSize": true,
              "layoutParameter": null,
              "opacity": 255,
              "positionPercentX": -0.041758243,
              "positionPercentY": 0.407643318,
              "positionType": 0,
              "rotation": 0,
              "scaleX": 1,
              "scaleY": 1,
              "sizePercentX": 0.7054945,
              "sizePercentY": 0.07643312,
              "sizeType": 0,
              "tag": 73835,
              "touchAble": false,
              "useMergedTexture": false,
              "visible": true,
              "width": 321,
              "x": -19,
              "y": 128,
              "areaHeight": 0,
              "areaWidth": 0,
              "fontFile": null,
              "fontName": "微软雅黑",
              "fontSize": 18,
              "hAlignment": 0,
              "text": "1.活动期间内新老用户均可参与本活动。",
              "touchScaleEnable": false,
              "vAlignment": 0
            }
          },
          {
            "classname": "Label",
            "name": null,
            "children": [],
            "options": {
              "__type": "LabelSurrogate:#EditorCommon.JsonModel.Component.GUI",
              "classname": "Label",
              "name": "Label_5_0",
              "ZOrder": 4,
              "actiontag": 51768328,
              "anchorPointX": 0.5,
              "anchorPointY": 0.5,
              "classType": "CocoStudio.EngineAdapterWrap.CSLabel",
              "colorB": 255,
              "colorG": 255,
              "colorR": 255,
              "customProperty": "",
              "flipX": false,
              "flipY": false,
              "height": 24,
              "ignoreSize": true,
              "layoutParameter": null,
              "opacity": 255,
              "positionPercentX": -0.0153846154,
              "positionPercentY": 0.318471342,
              "positionType": 0,
              "rotation": 0,
              "scaleX": 1,
              "scaleY": 1,
              "sizePercentX": 0.7582418,
              "sizePercentY": 0.07643312,
              "sizeType": 0,
              "tag": 73838,
              "touchAble": false,
              "useMergedTexture": false,
              "visible": true,
              "width": 345,
              "x": -7,
              "y": 100,
              "areaHeight": 0,
              "areaWidth": 0,
              "fontFile": null,
              "fontName": "微软雅黑",
              "fontSize": 18,
              "hAlignment": 0,
              "text": "2.抽奖会在用户单次充值金额≥2元同时输入",
              "touchScaleEnable": false,
              "vAlignment": 0
            }
          },
          {
            "classname": "Label",
            "name": null,
            "children": [],
            "options": {
              "__type": "LabelSurrogate:#EditorCommon.JsonModel.Component.GUI",
              "classname": "Label",
              "name": "Label_9_0",
              "ZOrder": 5,
              "actiontag": 27343545,
              "anchorPointX": 0.5,
              "anchorPointY": 0.5,
              "classType": "CocoStudio.EngineAdapterWrap.CSLabel",
              "colorB": 255,
              "colorG": 255,
              "colorR": 255,
              "customProperty": "",
              "flipX": false,
              "flipY": false,
              "height": 24,
              "ignoreSize": true,
              "layoutParameter": null,
              "opacity": 255,
              "positionPercentX": 0,
              "positionPercentY": 0.226114646,
              "positionType": 0,
              "rotation": 0,
              "scaleX": 1,
              "scaleY": 1,
              "sizePercentX": 0.7912088,
              "sizePercentY": 0.07643312,
              "sizeType": 0,
              "tag": 73841,
              "touchAble": false,
              "useMergedTexture": false,
              "visible": true,
              "width": 360,
              "x": 0,
              "y": 71,
              "areaHeight": 0,
              "areaWidth": 0,
              "fontFile": null,
              "fontName": "微软雅黑",
              "fontSize": 18,
              "hAlignment": 0,
              "text": "手机号后开启，充值次数越多抽奖次数越多。",
              "touchScaleEnable": false,
              "vAlignment": 0
            }
          },
          {
            "classname": "Label",
            "name": null,
            "children": [],
            "options": {
              "__type": "LabelSurrogate:#EditorCommon.JsonModel.Component.GUI",
              "classname": "Label",
              "name": "Label_9_1",
              "ZOrder": 4,
              "actiontag": 59280891,
              "anchorPointX": 0.5,
              "anchorPointY": 0.5,
              "classType": "CocoStudio.EngineAdapterWrap.CSLabel",
              "colorB": 255,
              "colorG": 255,
              "colorR": 255,
              "customProperty": "",
              "flipX": false,
              "flipY": false,
              "height": 24,
              "ignoreSize": true,
              "layoutParameter": null,
              "opacity": 255,
              "positionPercentX": -0.0109890113,
              "positionPercentY": 0.133757964,
              "positionType": 0,
              "rotation": 0,
              "scaleX": 1,
              "scaleY": 1,
              "sizePercentX": 0.7692308,
              "sizePercentY": 0.07643312,
              "sizeType": 0,
              "tag": 73843,
              "touchAble": false,
              "useMergedTexture": false,
              "visible": true,
              "width": 350,
              "x": -5,
              "y": 42,
              "areaHeight": 0,
              "areaWidth": 0,
              "fontFile": null,
              "fontName": "微软雅黑",
              "fontSize": 18,
              "hAlignment": 0,
              "text": "3.部分活动奖品会在活动结束后的3个工作日",
              "touchScaleEnable": false,
              "vAlignment": 0
            }
          },
          {
            "classname": "Label",
            "name": null,
            "children": [],
            "options": {
              "__type": "LabelSurrogate:#EditorCommon.JsonModel.Component.GUI",
              "classname": "Label",
              "name": "Label_9_2",
              "ZOrder": 5,
              "actiontag": 2351288,
              "anchorPointX": 0.5,
              "anchorPointY": 0.5,
              "classType": "CocoStudio.EngineAdapterWrap.CSLabel",
              "colorB": 255,
              "colorG": 255,
              "colorR": 255,
              "customProperty": "",
              "flipX": false,
              "flipY": false,
              "height": 24,
              "ignoreSize": true,
              "layoutParameter": null,
              "opacity": 255,
              "positionPercentX": 0,
              "positionPercentY": 0.0414012745,
              "positionType": 0,
              "rotation": 0,
              "scaleX": 1,
              "scaleY": 1,
              "sizePercentX": 0.7912088,
              "sizePercentY": 0.07643312,
              "sizeType": 0,
              "tag": 73845,
              "touchAble": false,
              "useMergedTexture": false,
              "visible": true,
              "width": 360,
              "x": 0,
              "y": 13,
              "areaHeight": 0,
              "areaWidth": 0,
              "fontFile": null,
              "fontName": "微软雅黑",
              "fontSize": 18,
              "hAlignment": 0,
              "text": "内，根据玩家留下来的真实有效的手机号进行",
              "touchScaleEnable": false,
              "vAlignment": 0
            }
          },
          {
            "classname": "Label",
            "name": null,
            "children": [],
            "options": {
              "__type": "LabelSurrogate:#EditorCommon.JsonModel.Component.GUI",
              "classname": "Label",
              "name": "Label_9_3",
              "ZOrder": 5,
              "actiontag": 569920,
              "anchorPointX": 0.5,
              "anchorPointY": 0.5,
              "classType": "CocoStudio.EngineAdapterWrap.CSLabel",
              "colorB": 255,
              "colorG": 255,
              "colorR": 255,
              "customProperty": "",
              "flipX": false,
              "flipY": false,
              "height": 24,
              "ignoreSize": true,
              "layoutParameter": null,
              "opacity": 255,
              "positionPercentX": -0.00659340667,
              "positionPercentY": -0.0509554148,
              "positionType": 0,
              "rotation": 0,
              "scaleX": 1,
              "scaleY": 1,
              "sizePercentX": 0.7758242,
              "sizePercentY": 0.07643312,
              "sizeType": 0,
              "tag": 73847,
              "touchAble": false,
              "useMergedTexture": false,
              "visible": true,
              "width": 353,
              "x": -3,
              "y": -16,
              "areaHeight": 0,
              "areaWidth": 0,
              "fontFile": null,
              "fontName": "微软雅黑",
              "fontSize": 18,
              "hAlignment": 0,
              "text": "核对，并在7个工作日内发放奖品，在此期间",
              "touchScaleEnable": false,
              "vAlignment": 0
            }
          },
          {
            "classname": "Label",
            "name": null,
            "children": [],
            "options": {
              "__type": "LabelSurrogate:#EditorCommon.JsonModel.Component.GUI",
              "classname": "Label",
              "name": "Label_9_4",
              "ZOrder": 5,
              "actiontag": 7028863,
              "anchorPointX": 0.5,
              "anchorPointY": 0.5,
              "classType": "CocoStudio.EngineAdapterWrap.CSLabel",
              "colorB": 255,
              "colorG": 255,
              "colorR": 255,
              "customProperty": "",
              "flipX": false,
              "flipY": false,
              "height": 24,
              "ignoreSize": true,
              "layoutParameter": null,
              "opacity": 255,
              "positionPercentX": -0.0989011,
              "positionPercentY": -0.1433121,
              "positionType": 0,
              "rotation": 0,
              "scaleX": 1,
              "scaleY": 1,
              "sizePercentX": 0.5934066,
              "sizePercentY": 0.07643312,
              "sizeType": 0,
              "tag": 73849,
              "touchAble": false,
              "useMergedTexture": false,
              "visible": true,
              "width": 270,
              "x": -45,
              "y": -45,
              "areaHeight": 0,
              "areaWidth": 0,
              "fontFile": null,
              "fontName": "微软雅黑",
              "fontSize": 18,
              "hAlignment": 0,
              "text": "内，用户无消息回复将视为放弃。",
              "touchScaleEnable": false,
              "vAlignment": 0
            }
          },
          {
            "classname": "Label",
            "name": null,
            "children": [],
            "options": {
              "__type": "LabelSurrogate:#EditorCommon.JsonModel.Component.GUI",
              "classname": "Label",
              "name": "Label_9_5",
              "ZOrder": 5,
              "actiontag": 52756515,
              "anchorPointX": 0.5,
              "anchorPointY": 0.5,
              "classType": "CocoStudio.EngineAdapterWrap.CSLabel",
              "colorB": 255,
              "colorG": 255,
              "colorR": 255,
              "customProperty": "",
              "flipX": false,
              "flipY": false,
              "height": 24,
              "ignoreSize": true,
              "layoutParameter": null,
              "opacity": 255,
              "positionPercentX": -0.0021978023,
              "positionPercentY": -0.2356688,
              "positionType": 0,
              "rotation": 0,
              "scaleX": 1,
              "scaleY": 1,
              "sizePercentX": 0.7846154,
              "sizePercentY": 0.07643312,
              "sizeType": 0,
              "tag": 73851,
              "touchAble": false,
              "useMergedTexture": false,
              "visible": true,
              "width": 357,
              "x": -1,
              "y": -74,
              "areaHeight": 0,
              "areaWidth": 0,
              "fontFile": null,
              "fontName": "微软雅黑",
              "fontSize": 18,
              "hAlignment": 0,
              "text": "4.活动最终解释权归嘉丰永道（北京）科技有",
              "touchScaleEnable": false,
              "vAlignment": 0
            }
          },
          {
            "classname": "ImageView",
            "name": null,
            "children": [],
            "options": {
              "__type": "ImageViewSurrogate:#EditorCommon.JsonModel.Component.GUI",
              "classname": "ImageView",
              "name": "bg",
              "ZOrder": 0,
              "actiontag": 46100330,
              "anchorPointX": 0.5,
              "anchorPointY": 0.5,
              "classType": "CocoStudio.EngineAdapterWrap.CSImageView",
              "colorB": 255,
              "colorG": 255,
              "colorR": 255,
              "customProperty": "",
              "flipX": false,
              "flipY": false,
              "height": 450,
              "ignoreSize": false,
              "layoutParameter": null,
              "opacity": 255,
              "positionPercentX": 0,
              "positionPercentY": 0,
              "positionType": 0,
              "rotation": 0,
              "scaleX": 1,
              "scaleY": 1,
              "sizePercentX": 1,
              "sizePercentY": 1.433121,
              "sizeType": 0,
              "tag": 73852,
              "touchAble": false,
              "useMergedTexture": false,
              "visible": true,
              "width": 455,
              "x": 0,
              "y": 0,
              "capInsetsHeight": 1,
              "capInsetsWidth": 1,
              "capInsetsX": 0,
              "capInsetsY": 62,
              "fileName": null,
              "fileNameData": {
                "path": "smdb.png",
                "plistFile": "",
                "resourceType": 0
              },
              "scale9Enable": true,
              "scale9Height": 450,
              "scale9Width": 455
            }
          },
          {
            "classname": "Label",
            "name": null,
            "children": [],
            "options": {
              "__type": "LabelSurrogate:#EditorCommon.JsonModel.Component.GUI",
              "classname": "Label",
              "name": "Label_9_6",
              "ZOrder": 4,
              "actiontag": 15637223,
              "anchorPointX": 0.5,
              "anchorPointY": 0.5,
              "classType": "CocoStudio.EngineAdapterWrap.CSLabel",
              "colorB": 255,
              "colorG": 255,
              "colorR": 255,
              "customProperty": "",
              "flipX": false,
              "flipY": false,
              "height": 24,
              "ignoreSize": true,
              "layoutParameter": null,
              "opacity": 255,
              "positionPercentX": -0.2769231,
              "positionPercentY": -0.3280255,
              "positionType": 0,
              "rotation": 0,
              "scaleX": 1,
              "scaleY": 1,
              "sizePercentX": 0.237362638,
              "sizePercentY": 0.07643312,
              "sizeType": 0,
              "tag": 73854,
              "touchAble": false,
              "useMergedTexture": false,
              "visible": true,
              "width": 108,
              "x": -126,
              "y": -103,
              "areaHeight": 0,
              "areaWidth": 0,
              "fontFile": null,
              "fontName": "微软雅黑",
              "fontSize": 18,
              "hAlignment": 0,
              "text": "限公司所有。",
              "touchScaleEnable": false,
              "vAlignment": 0
            }
          },
          {
            "classname": "Label",
            "name": null,
            "children": [],
            "options": {
              "__type": "LabelSurrogate:#EditorCommon.JsonModel.Component.GUI",
              "classname": "Label",
              "name": "Label_9_11_14",
              "ZOrder": 4,
              "actiontag": 52998303,
              "anchorPointX": 0.5,
              "anchorPointY": 0.5,
              "classType": "CocoStudio.EngineAdapterWrap.CSLabel",
              "colorB": 255,
              "colorG": 255,
              "colorR": 255,
              "customProperty": "",
              "flipX": false,
              "flipY": false,
              "height": 24,
              "ignoreSize": true,
              "layoutParameter": null,
              "opacity": 255,
              "positionPercentX": -0.0153846154,
              "positionPercentY": -0.4522293,
              "positionType": 0,
              "rotation": 0,
              "scaleX": 1,
              "scaleY": 1,
              "sizePercentX": 0.8747253,
              "sizePercentY": 0.07643312,
              "sizeType": 0,
              "tag": 73870,
              "touchAble": false,
              "useMergedTexture": false,
              "visible": true,
              "width": 398,
              "x": -7,
              "y": -142,
              "areaHeight": 0,
              "areaWidth": 0,
              "fontFile": null,
              "fontName": "微软雅黑",
              "fontSize": 18,
              "hAlignment": 0,
              "text": "如有问题请联系客服，客服电话：4001091109。",
              "touchScaleEnable": false,
              "vAlignment": 0
            }
          }
        ],
        "options": {
          "__type": "ImageViewSurrogate:#EditorCommon.JsonModel.Component.GUI",
          "classname": "ImageView",
          "name": "Bg",
          "ZOrder": 0,
          "actiontag": 40036410,
          "anchorPointX": 0.5,
          "anchorPointY": 0.5,
          "classType": "CocoStudio.EngineAdapterWrap.CSImageView",
          "colorB": 255,
          "colorG": 255,
          "colorR": 255,
          "customProperty": "",
          "flipX": false,
          "flipY": false,
          "height": 314,
          "ignoreSize": false,
          "layoutParameter": null,
          "opacity": 255,
          "positionPercentX": 0.5,
          "positionPercentY": 0.5575,
          "positionType": 0,
          "rotation": 0,
          "scaleX": 1,
          "scaleY": 1,
          "sizePercentX": 0.9479167,
          "sizePercentY": 0.3925,
          "sizeType": 0,
          "tag": 73394,
          "touchAble": false,
          "useMergedTexture": false,
          "visible": true,
          "width": 455,
          "x": 240,
          "y": 446,
          "capInsetsHeight": 1,
          "capInsetsWidth": 1,
          "capInsetsX": 0,
          "capInsetsY": 0,
          "fileName": null,
          "fileNameData": {
            "path": "white.png",
            "plistFile": "",
            "resourceType": 0
          },
          "scale9Enable": false,
          "scale9Height": 314,
          "scale9Width": 455
        }
      }
    ],
    "options": {
      "__type": "PanelSurrogate:#EditorCommon.JsonModel.Component.GUI",
      "classname": "Panel",
      "name": "PanelGiftLotreryRule",
      "ZOrder": 0,
      "actiontag": -1,
      "anchorPointX": 0,
      "anchorPointY": 0,
      "classType": "CocoStudio.EngineAdapterWrap.CSPanel",
      "colorB": 255,
      "colorG": 255,
      "colorR": 255,
      "customProperty": "",
      "flipX": false,
      "flipY": false,
      "height": 800,
      "ignoreSize": false,
      "layoutParameter": null,
      "opacity": 255,
      "positionPercentX": 0,
      "positionPercentY": 0,
      "positionType": 0,
      "rotation": 0,
      "scaleX": 1,
      "scaleY": 1,
      "sizePercentX": 1,
      "sizePercentY": 1,
      "sizeType": 0,
      "tag": 73393,
      "touchAble": true,
      "useMergedTexture": false,
      "visible": true,
      "width": 480,
      "x": 0,
      "y": 0,
      "adaptScreen": false,
      "backGroundImage": null,
      "backGroundImageData": null,
      "backGroundScale9Enable": false,
      "bgColorB": 255,
      "bgColorG": 200,
      "bgColorOpacity": 0,
      "bgColorR": 150,
      "bgEndColorB": 255,
      "bgEndColorG": 200,
      "bgEndColorR": 150,
      "bgStartColorB": 255,
      "bgStartColorG": 255,
      "bgStartColorR": 255,
      "capInsetsHeight": 1,
      "capInsetsWidth": 1,
      "capInsetsX": 0,
      "capInsetsY": 0,
      "clipAble": false,
      "colorType": 1,
      "layoutType": 0,
      "vectorX": 0,
      "vectorY": -0.5
    }
  }
}